py3helpers/__init__.py
py3helpers/__main__.py
py3helpers/aws.py
py3helpers/classification.py
py3helpers/cli.py
py3helpers/multiprocess.py
py3helpers/seq_tools.py
py3helpers/utils.py
py3helpers/scripts/__init__.py
py3helpers/scripts/merge_methyl_bed_files.py
py3helpers/scripts/methyl_bed_kmer_analysis.py
py3helpers-0.5.0.data/scripts/merge_methyl_bed_files.py
py3helpers-0.5.0.dist-info/AUTHORS.rst
py3helpers-0.5.0.dist-info/LICENSE
py3helpers-0.5.0.dist-info/METADATA
py3helpers-0.5.0.dist-info/WHEEL
py3helpers-0.5.0.dist-info/entry_points.txt
py3helpers-0.5.0.dist-info/top_level.txt
py3helpers-0.5.0.dist-info/RECORD
